context_haystack/__init__.py
context_haystack/context.py
context_haystack-0.0.0.dist-info/LICENSE
context_haystack-0.0.0.dist-info/METADATA
context_haystack-0.0.0.dist-info/WHEEL
context_haystack-0.0.0.dist-info/top_level.txt
context_haystack-0.0.0.dist-info/RECORD
