Metadata-Version: 2.1
Name: context-haystack
Version: 0.0.0
Author-email: Alec Barber <alec@context.ai>, Alex Gamble <alex@context.ai>, Amisha Singh <amisha@context.ai>
Project-URL: Documentation, https://docs.context.ai
Project-URL: Issues, https://github.com/contextco/context-haystack/issues
Project-URL: Source, https://github.com/contextco/context-haystack
Requires-Python: >=3.9
License-File: LICENSE
Requires-Dist: haystack-ai
Requires-Dist: context-python
